get_folder_file/__init__.py
get_folder_file/get_file_list.py
get_folder_file-0.4.0.dist-info/METADATA
get_folder_file-0.4.0.dist-info/WHEEL
get_folder_file-0.4.0.dist-info/top_level.txt
get_folder_file-0.4.0.dist-info/RECORD
