Metadata-Version: 2.1
Name: get-folder-file
Version: 0.4.0
Summary: This is a python wrapper library for the get file list in a folder
Home-page: https://gitlab.chq.ei/north-asia/getfilelistfromfolder.git
Author: Greg He
Author-email: greg.he@expeditors.com
License: MIT
Platform: UNKNOWN
Requires-Dist: requests
